MANIFEST.in
README.rst
VERSION
conftest.py
requirements.txt
setup.cfg
setup.py
PyKleen.egg-info/PKG-INFO
PyKleen.egg-info/SOURCES.txt
PyKleen.egg-info/dependency_links.txt
PyKleen.egg-info/requires.txt
PyKleen.egg-info/top_level.txt
docs/Makefile
docs/conf.py
docs/development.rst
docs/example.inc.rst
docs/index.rst
docs/structure.rst
docs/tests.rst
pykleen/__init__.py
pykleen/utils.py
tests/test_default.py
tests/test_flat.py
tests/test_package.py
tests/test_schema.py