Metadata-Version: 1.1
Name: PyKleen
Version: 1.5
Summary: Input; simple, clean.
Home-page: https://bitbucket.org/creeerio/pykleen
Author: Nils Corver
Author-email: nils@creeer.io
License: MIT
Platform: UNKNOWN
Classifier: Development Status :: 3 - Alpha
Classifier: Intended Audience :: Developers
Classifier: License :: OSI Approved :: MIT License
Classifier: Programming Language :: Python :: 3.5
